embedding_quality/__init__.py
embedding_quality/evaluation.py
embedding_quality-0.1.1.dist-info/METADATA
embedding_quality-0.1.1.dist-info/WHEEL
embedding_quality-0.1.1.dist-info/top_level.txt
embedding_quality-0.1.1.dist-info/RECORD
