Metadata-Version: 2.1
Name: embedding-quality
Version: 0.1.1
Summary: A package for unsupervised embedding quality evaluation
Home-page: https://github.com/yourusername/embedding_quality
Author: Raghav Awasthi
Author-email: rxa615@case.edu
Classifier: Programming Language :: Python :: 3
Classifier: License :: OSI Approved :: MIT License
Classifier: Operating System :: OS Independent
Requires-Python: >=3.6
Requires-Dist: numpy >=1.18.0
